countdown_tddschn/__init__.py
countdown_tddschn/bin/simple_countdown.py
countdown_tddschn/classes.py
countdown_tddschn/utils.py
countdown_tddschn-0.3.4.dist-info/entry_points.txt
countdown_tddschn-0.3.4.dist-info/LICENSE
countdown_tddschn-0.3.4.dist-info/WHEEL
countdown_tddschn-0.3.4.dist-info/METADATA
countdown_tddschn-0.3.4.dist-info/RECORD
